xaibo/__init__.py
xaibo/cli/__init__.py
xaibo/core/__init__.py
xaibo/core/agent.py
xaibo/core/config.py
xaibo/core/exchange.py
xaibo/core/registry.py
xaibo/core/xaibo.py
xaibo/core/models/__init__.py
xaibo/core/models/events.py
xaibo/core/models/llm.py
xaibo/core/models/response.py
xaibo/core/models/tools.py
xaibo/core/protocols/__init__.py
xaibo/core/protocols/conversation.py
xaibo/core/protocols/llm.py
xaibo/core/protocols/memory.py
xaibo/core/protocols/message_handlers.py
xaibo/core/protocols/response.py
xaibo/core/protocols/tools.py
xaibo/integrations/__init__.py
xaibo/integrations/livekit/__init__.py
xaibo/integrations/livekit/agent_loader.py
xaibo/integrations/livekit/llm.py
xaibo/integrations/livekit/log.py
xaibo/integrations/livekit/version.py
xaibo/primitives/__init__.py
xaibo/primitives/event_listeners/__init__.py
xaibo/primitives/event_listeners/debug_event_listener.py
xaibo/primitives/modules/__init__.py
xaibo/primitives/modules/response.py
xaibo/primitives/modules/conversation/__init__.py
xaibo/primitives/modules/conversation/conversation.py
xaibo/primitives/modules/llm/__init__.py
xaibo/primitives/modules/llm/anthropic.py
xaibo/primitives/modules/llm/bedrock.py
xaibo/primitives/modules/llm/combinator.py
xaibo/primitives/modules/llm/google.py
xaibo/primitives/modules/llm/mock.py
xaibo/primitives/modules/llm/openai.py
xaibo/primitives/modules/memory/__init__.py
xaibo/primitives/modules/memory/huggingface_embedder.py
xaibo/primitives/modules/memory/memory_provider.py
xaibo/primitives/modules/memory/numpy_vector_index.py
xaibo/primitives/modules/memory/openai_embedder.py
xaibo/primitives/modules/memory/sentence_transformer_embedder.py
xaibo/primitives/modules/memory/token_chunker.py
xaibo/primitives/modules/memory/vector_memory.py
xaibo/primitives/modules/orchestrator/__init__.py
xaibo/primitives/modules/orchestrator/react_orchestrator.py
xaibo/primitives/modules/orchestrator/simple_tool_orchestrator.py
xaibo/primitives/modules/tools/__init__.py
xaibo-0.2.0.dist-info/METADATA
xaibo-0.2.0.dist-info/WHEEL
xaibo-0.2.0.dist-info/entry_points.txt
xaibo-0.2.0.dist-info/licenses/LICENSE
xaibo-0.2.0.dist-info/RECORD
