Metadata-Version: 2.4
Name: xaibo
Version: 0.2.0
Summary: Xaibo is a framework for building powerful, transparent, and modular AI agents.
Author-email: Xpress AI <hello@xpress.ai>
License-File: LICENSE
Keywords: AI,agent,framework,modular
Classifier: Intended Audience :: Developers
Classifier: License :: OSI Approved :: Apache Software License
Classifier: Programming Language :: Python :: 3
Classifier: Programming Language :: Python :: 3 :: Only
Classifier: Programming Language :: Python :: 3.10
Classifier: Programming Language :: Python :: 3.11
Classifier: Programming Language :: Python :: 3.12
Classifier: Programming Language :: Python :: 3.13
Classifier: Topic :: Multimedia :: Sound/Audio
Classifier: Topic :: Multimedia :: Video
Classifier: Topic :: Scientific/Engineering :: Artificial Intelligence
Requires-Python: >=3.10
Requires-Dist: aiohttp>=3.8.0
Requires-Dist: docstring-parser>=0.16
Requires-Dist: mkdocs-llmstxt>=0.2.0
Requires-Dist: numpy<2.0.0,>=1.0.0; sys_platform == 'darwin' and platform_machine == 'x86_64'
Requires-Dist: numpy>=2.2.5; sys_platform != 'darwin' or platform_machine != 'x86_64'
Requires-Dist: pydantic-yaml>=1.4.0
Requires-Dist: pydantic>=2.10.6
Requires-Dist: pytest-asyncio>=0.25.3
Requires-Dist: pytest>=8.3.4
Requires-Dist: questionary>=2.1.0
Requires-Dist: websockets>=11.0.0
Provides-Extra: anthropic
Requires-Dist: anthropic>=0.49.0; extra == 'anthropic'
Provides-Extra: bedrock
Requires-Dist: boto3>=1.37.38; extra == 'bedrock'
Provides-Extra: google
Requires-Dist: google-genai>=1.5.0; extra == 'google'
Provides-Extra: livekit
Requires-Dist: livekit-agents>=1.0.22; extra == 'livekit'
Provides-Extra: local
Requires-Dist: sentence-transformers>=4.1.0; extra == 'local'
Requires-Dist: soundfile>=0.13.1; extra == 'local'
Requires-Dist: tiktoken>=0.9.0; extra == 'local'
Requires-Dist: torch<2.3.0,>=2.2.0; (sys_platform == 'darwin' and platform_machine == 'x86_64') and extra == 'local'
Requires-Dist: torch>=2.3.0; (sys_platform != 'darwin' or platform_machine != 'x86_64') and extra == 'local'
Requires-Dist: transformers>=4.51.3; extra == 'local'
Provides-Extra: openai
Requires-Dist: openai>=1.65.4; extra == 'openai'
Provides-Extra: webserver
Requires-Dist: fastapi[standard]>=0.115.12; extra == 'webserver'
Requires-Dist: python-dotenv>=1.1.0; extra == 'webserver'
Requires-Dist: strawberry-graphql>=0.262.5; extra == 'webserver'
Requires-Dist: strawberry-graphql[cli]>=0.262.5; extra == 'webserver'
Requires-Dist: watchfiles>=1.0.4; extra == 'webserver'
